LICENSE.txt
MANIFEST.in
README.rst
setup.cfg
setup.py
bsdgames/__init__.py
bsdgames/_pom.py
bsdgames.egg-info/PKG-INFO
bsdgames.egg-info/SOURCES.txt
bsdgames.egg-info/dependency_links.txt
bsdgames.egg-info/requires.txt
bsdgames.egg-info/top_level.txt