Metadata-Version: 1.1
Name: bsdgames
Version: 0.0.7
Summary: BSD Games is a collection of the classic text based games distributed with some BSDs like FreeBSD and NetBSD.
Home-page: https://github.com/lucyking/python-bsdgames
Author: lucyking
Author-email: joehisaishi1943@gmail.com
License: BSD
Keywords: bsdgames bsd-games bsdgame
Platform: UNKNOWN
Classifier: Development Status :: 3 - Alpha
Classifier: Intended Audience :: Developers
Classifier: Topic :: Software Development :: Build Tools
Classifier: License :: OSI Approved :: BSD License
Classifier: Programming Language :: Python :: 2
Classifier: Programming Language :: Python :: 2.6
Classifier: Programming Language :: Python :: 2.7
Classifier: Programming Language :: Python :: 3
Classifier: Programming Language :: Python :: 3.2
Classifier: Programming Language :: Python :: 3.3
Classifier: Programming Language :: Python :: 3.4
Classifier: Programming Language :: Python :: 3.5
